{
  "model_name": "infy",
  "version": "v2",
  "trained_at": "2026-04-13T21:55:29.005896",
  "samples": 403,
  "up_count": 205,
  "down_count": 198,
  "features_total": 52,
  "features_selected": 37,
  "train_accuracy": 0.8333,
  "test_accuracy": 0.5802,
  "auc": 0.5985,
  "precision": 0.52,
  "recall": 0.7222,
  "f1": 0.6047,
  "forward_periods": 5,
  "purge_gap": 10,
  "top_features": {
    "month_sin": 0.0725,
    "wq_alpha042": 0.0516,
    "atr_ratio": 0.0515,
    "month_cos": 0.0466,
    "cci_20": 0.0461,
    "stoch_k": 0.0461,
    "kyle_lambda": 0.0438,
    "mfi_14": 0.0431,
    "sma_20_50_cross": 0.0418,
    "vol_regime": 0.0401,
    "price_vs_vwap": 0.0385,
    "rsi_14": 0.0345,
    "wq_alpha041": 0.0337,
    "sma_slope_20": 0.0322,
    "spread_proxy": 0.0303
  }
}